imjoy_jupyterlab_extension/__init__.py
imjoy_jupyterlab_extension/_version.py
imjoy_jupyterlab_extension-0.2.5.data/data/share/jupyter/labextensions/imjoy-jupyterlab-extension/build_log.json
imjoy_jupyterlab_extension-0.2.5.data/data/share/jupyter/labextensions/imjoy-jupyterlab-extension/package.json
imjoy_jupyterlab_extension-0.2.5.data/data/share/jupyter/labextensions/imjoy-jupyterlab-extension/static/lib_index_js.9b49eabf628b7b47bd8a.js
imjoy_jupyterlab_extension-0.2.5.data/data/share/jupyter/labextensions/imjoy-jupyterlab-extension/static/lib_index_js.9b49eabf628b7b47bd8a.js.map
imjoy_jupyterlab_extension-0.2.5.data/data/share/jupyter/labextensions/imjoy-jupyterlab-extension/static/remoteEntry.255b911990d2e3135de9.js
imjoy_jupyterlab_extension-0.2.5.data/data/share/jupyter/labextensions/imjoy-jupyterlab-extension/static/remoteEntry.255b911990d2e3135de9.js.map
imjoy_jupyterlab_extension-0.2.5.data/data/share/jupyter/labextensions/imjoy-jupyterlab-extension/static/style.js
imjoy_jupyterlab_extension-0.2.5.data/data/share/jupyter/labextensions/imjoy-jupyterlab-extension/static/style_index_js.4a04af2efb9bedd57803.js
imjoy_jupyterlab_extension-0.2.5.data/data/share/jupyter/labextensions/imjoy-jupyterlab-extension/static/style_index_js.4a04af2efb9bedd57803.js.map
imjoy_jupyterlab_extension-0.2.5.data/data/share/jupyter/labextensions/imjoy-jupyterlab-extension/static/vendors-node_modules_imjoy-core_dist_imjoy-loader_js-node_modules_imjoy-core_dist_imjoy-rpc_js.fa1a9cd9c57812bbe9b2.js
imjoy_jupyterlab_extension-0.2.5.data/data/share/jupyter/labextensions/imjoy-jupyterlab-extension/static/vendors-node_modules_imjoy-core_dist_imjoy-loader_js-node_modules_imjoy-core_dist_imjoy-rpc_js.fa1a9cd9c57812bbe9b2.js.map
imjoy_jupyterlab_extension-0.2.5.data/data/share/jupyter/labextensions/imjoy-jupyterlab-extension/static/vendors-node_modules_reflect-metadata_Reflect_js.91708819816796d39b60.js
imjoy_jupyterlab_extension-0.2.5.dist-info/METADATA
imjoy_jupyterlab_extension-0.2.5.dist-info/WHEEL
imjoy_jupyterlab_extension-0.2.5.dist-info/licenses/LICENSE
imjoy_jupyterlab_extension-0.2.5.dist-info/RECORD
