Metadata-Version: 2.1
Name: imjoy_jupyterlab_extension
Version: 0.2.5
Summary: Run ImJoy plugins in JupyterLab
Project-URL: Homepage, https://github.com/imjoy-team/imjoy-jupyterlab-extension
Project-URL: Bug Tracker, https://github.com/imjoy-team/imjoy-jupyterlab-extension/issues
Project-URL: Repository, https://github.com/imjoy-team/imjoy-jupyterlab-extension.git
Author-email: Wei Ouyang <oeway007@gmail.com>
License: BSD 3-Clause License
License-File: LICENSE
Classifier: Framework :: Jupyter
Classifier: Framework :: Jupyter :: JupyterLab
Classifier: Framework :: Jupyter :: JupyterLab :: 4
Classifier: Framework :: Jupyter :: JupyterLab :: Extensions
Classifier: Framework :: Jupyter :: JupyterLab :: Extensions :: Prebuilt
Classifier: License :: OSI Approved :: BSD License
Classifier: Programming Language :: Python
Classifier: Programming Language :: Python :: 3
Classifier: Programming Language :: Python :: 3.8
Classifier: Programming Language :: Python :: 3.9
Classifier: Programming Language :: Python :: 3.10
Classifier: Programming Language :: Python :: 3.11
Classifier: Programming Language :: Python :: 3.12
Requires-Python: >=3.8
Requires-Dist: imjoy-rpc
